Metadata-Version: 2.1
Name: package-helper-2-test
Version: 0.2.0
Summary: Package Helper 2 Test is a test of Package Helper 2.
Home-page: https://github.com/francois-durand/package_helper_2_test
Author: François Durand
Author-email: fradurand@gmail.com
License: GNU General Public License v3
Keywords: package_helper_2_test
Platform: UNKNOWN
Classifier: Development Status :: 2 - Pre-Alpha
Classifier: Intended Audience :: Developers
Classifier: License :: OSI Approved :: GNU General Public License v3 (GPLv3)
Classifier: Natural Language :: English
Classifier: Programming Language :: Python :: 3
Classifier: Programming Language :: Python :: 3.6
Classifier: Programming Language :: Python :: 3.7
Classifier: Programming Language :: Python :: 3.8
Requires-Python: >=3.6
